opigen/__init__.py
opigen/config/__init__.py
opigen/config/attr.toml
opigen/config/color.def
opigen/config/font.def
opigen/contrib/__init__.py
opigen/contrib/widgets.py
opigen/opimodel/__init__.py
opigen/opimodel/actions.py
opigen/opimodel/borders.py
opigen/opimodel/colors.py
opigen/opimodel/fonts.py
opigen/opimodel/rules.py
opigen/opimodel/scalings.py
opigen/opimodel/scripts.py
opigen/opimodel/utils.py
opigen/opimodel/widgets.py
opigen/renderers/__init__.py
opigen/renderers/css/__init__.py
opigen/renderers/css/actions.py
opigen/renderers/css/borders.py
opigen/renderers/css/colors.py
opigen/renderers/css/fonts.py
opigen/renderers/css/points.py
opigen/renderers/css/render.py
opigen/renderers/css/rules.py
opigen/renderers/css/scalings.py
opigen/renderers/css/scripts.py
opigen/renderers/css/tabs.py
opigen/renderers/css/text.py
opigen/renderers/css/widget.py
opigen/renderers/phoebus/__init__.py
opigen/renderers/phoebus/actions.py
opigen/renderers/phoebus/axes.py
opigen/renderers/phoebus/borders.py
opigen/renderers/phoebus/colors.py
opigen/renderers/phoebus/fonts.py
opigen/renderers/phoebus/points.py
opigen/renderers/phoebus/render.py
opigen/renderers/phoebus/rules.py
opigen/renderers/phoebus/scalings.py
opigen/renderers/phoebus/scripts.py
opigen/renderers/phoebus/tabs.py
opigen/renderers/phoebus/text.py
opigen/renderers/phoebus/traces.py
opigen/renderers/phoebus/widget.py
opigen-1.0.6.dist-info/LICENSE
opigen-1.0.6.dist-info/METADATA
opigen-1.0.6.dist-info/WHEEL
opigen-1.0.6.dist-info/entry_points.txt
opigen-1.0.6.dist-info/top_level.txt
opigen-1.0.6.dist-info/RECORD
