Metadata-Version: 2.1
Name: opigen
Version: 1.0.6
Summary: OPI Generation for CS-Studio and Phoebus
Home-page: https://github.com/archman/opi-generator
Author: Tong Zhang
Author-email: zhangt@frib.msu.edu
License: APACHE
Keywords: CS-Studio Phoebus OPI XML
Platform: UNKNOWN
Classifier: Programming Language :: Python :: 3
Classifier: Topic :: Scientific/Engineering
Classifier: Topic :: Software Development :: Libraries :: Python Modules
Requires-Dist: lxml
